genomen/__init__.py
genomen/base_config.py
genomen/run_manager.py
genomen/utils.py
genomen/model/models.json
genomen-0.1.4.dist-info/METADATA
genomen-0.1.4.dist-info/WHEEL
genomen-0.1.4.dist-info/top_level.txt
genomen-0.1.4.dist-info/RECORD
