Metadata-Version: 2.4
Name: genomen
Version: 0.1.4
Summary: Polygenic Risk and Association beyond Linearity
License-Expression: Apache-2.0
Project-URL: Repository, https://github.com/AI-sandbox/genomen
Project-URL: Issues, https://github.com/AI-sandbox/genomen/issues
Keywords: polygenic risk,ensemble learning
Classifier: Operating System :: OS Independent
Classifier: Programming Language :: Python :: 3.11
Classifier: Programming Language :: Python :: 3.12
Classifier: Programming Language :: Python :: 3.13
Classifier: Programming Language :: Python :: 3.14
Requires-Python: >=3.11
Requires-Dist: fire>=0.7.0
Requires-Dist: matplotlib>=3.8.4
Requires-Dist: numpy>=1.26.4
Requires-Dist: pandas>=2.2.3
Requires-Dist: python-dotenv>=1.0.1
Requires-Dist: pyyaml>=6.0.2
Requires-Dist: scikit-learn>=1.6.0
Requires-Dist: scikit-optimize>=0.10.2
Requires-Dist: shap>=0.46.0
Requires-Dist: tqdm>=4.67.1
Requires-Dist: wandb>=0.19.7
Requires-Dist: pyarrow>=19.0.1
Requires-Dist: pgenlib>=0.92.1
Requires-Dist: statsmodels>=0.14.4
Requires-Dist: joblib>=1.5.1
Requires-Dist: dacite>=1.9.2
Requires-Dist: plotly>=6.3.0
Requires-Dist: nbformat>=5.10.4
Requires-Dist: catboost>=1.2.7
Requires-Dist: lightgbm==4.5
Requires-Dist: xgboost>=2.1.4
Provides-Extra: dev
Requires-Dist: black>=25.1.0; extra == "dev"
Requires-Dist: ipykernel>=6.29.5; extra == "dev"
Requires-Dist: isort>=6.0.1; extra == "dev"
Requires-Dist: py-spy>=0.4.0; extra == "dev"
Requires-Dist: pyranges>=0.1.4; extra == "dev"
Requires-Dist: pytest>=8.3.5; extra == "dev"
Requires-Dist: seaborn>=0.11.0; extra == "dev"
Requires-Dist: umap-learn>=0.5.9.post2; extra == "dev"
Provides-Extra: gpu
Requires-Dist: torch>=2.5.0; extra == "gpu"
Requires-Dist: cudf-cu12<26,>=25.2; extra == "gpu"
Requires-Dist: cuml-cu12<26,>=25.2; extra == "gpu"
Requires-Dist: libcudf-cu12<26,>=25.2; extra == "gpu"
Requires-Dist: rmm-cu12<26,>=25.2; extra == "gpu"
Requires-Dist: raft-dask-cu12<26,>=25.2; extra == "gpu"
Requires-Dist: cupy-cuda12x<14,>=13.4; extra == "gpu"
Provides-Extra: dnn
Requires-Dist: torch>=2.5.0; extra == "dnn"
Requires-Dist: einops>=0.6.0; extra == "dnn"
Requires-Dist: jaxtyping>=0.2.0; extra == "dnn"
